README.txt
setup.py
etc/debug.ini
etc/site.zcml
src/d2m/__init__.py
src/d2m.wsgiapp.egg-info/PKG-INFO
src/d2m.wsgiapp.egg-info/SOURCES.txt
src/d2m.wsgiapp.egg-info/dependency_links.txt
src/d2m.wsgiapp.egg-info/entry_points.txt
src/d2m.wsgiapp.egg-info/namespace_packages.txt
src/d2m.wsgiapp.egg-info/not-zip-safe
src/d2m.wsgiapp.egg-info/requires.txt
src/d2m.wsgiapp.egg-info/top_level.txt
src/d2m/wsgiapp/__init__.py
src/d2m/wsgiapp/app.py
src/d2m/wsgiapp/configure.zcml
src/d2m/wsgiapp/ftesting.zcml
src/d2m/wsgiapp/publication.py
src/d2m/wsgiapp/tests.py
src/d2m/wsgiapp/app_templates/index.pt
src/d2m/wsgiapp/static/README.txt
