Metadata-Version: 1.0
Name: d2m.wsgiapp
Version: 0.2
Summary: WSGI based Grok without ZODB
Home-page: UNKNOWN
Author: d2m
Author-email: michael@d2m.at
License: ZPL
Platform: UNKNOWN
